{
  "parents": [
    "system:cdap-etl-batch[4.1.0-SNAPSHOT,10.0.0-SNAPSHOT)",
    "system:cdap-etl-realtime[4.1.0-SNAPSHOT,10.0.0-SNAPSHOT)",
    "system:cdap-data-pipeline[4.1.0-SNAPSHOT,10.0.0-SNAPSHOT)",
    "system:cdap-data-streams[4.1.0-SNAPSHOT,10.0.0-SNAPSHOT)"
  ],
  "properties": {
    "widgets.OracleExport-action": "{\"metadata\":{\"spec-version\":\"1.0\"},\"configuration-groups\":[{\"label\":\"Oracle Export Properties\",\"properties\":[{\"widget-type\":\"textbox\",\"label\":\"Oracle Server Hostname\",\"name\":\"oracleServerHostname\"},{\"widget-type\":\"textbox\",\"label\":\"Oracle Server Port\",\"name\":\"oracleServerSSHPort\"},{\"widget-type\":\"textbox\",\"label\":\"Oracle Server Username\",\"name\":\"oracleServerSSHUsername\"},{\"widget-type\":\"select\",\"label\":\"Authentication Mechanism\",\"name\":\"oracleServerSSHAuthMechanism\",\"widget-attributes\":{\"values\":[\"Password\",\"Private key\"],\"default\":\"Password\"}},{\"widget-type\":\"password\",\"label\":\"Oracle Server Password\",\"name\":\"oracleServerSSHPassword\"},{\"widget-type\":\"textarea\",\"label\":\"Oracle Server Private Key\",\"name\":\"oracleServerSSHPrivateKey\"},{\"widget-type\":\"password\",\"label\":\"Private Key Passphrase\",\"name\":\"oracleServerSSHPassphrase\"},{\"widget-type\":\"textbox\",\"label\":\"Username to connect to Oracle DB\",\"name\":\"dbUsername\"},{\"widget-type\":\"password\",\"label\":\"Password to connect to Oracle DB\",\"name\":\"dbPassword\"},{\"widget-type\":\"textbox\",\"label\":\"Path of the ORACLE_HOME\",\"name\":\"oracleHome\"},{\"widget-type\":\"textbox\",\"label\":\"SID\",\"name\":\"oracleSID\"},{\"widget-type\":\"textarea\",\"label\":\"Query to be executed for export\",\"name\":\"queryToExecute\",\"widget-attributes\":{\"rows\":\"4\"}},{\"widget-type\":\"textbox\",\"label\":\"Full path of the temporary SQL script file to be created\",\"name\":\"tmpSQLScriptFile\"},{\"widget-type\":\"textarea\",\"label\":\"Oracle command to export the data\",\"name\":\"commandToRun\"},{\"widget-type\":\"textbox\",\"label\":\"Path where output file to be exported\",\"name\":\"outputPath\"},{\"widget-type\":\"select\",\"label\":\"Format\",\"name\":\"format\",\"widget-attributes\":{\"values\":[\"CSV\",\"PSV\",\"TSV\"],\"default\":\"CSV\"}}]}],\"outputs\":[]}",
    "doc.OracleExport-action": "# Oracle Export Action\n\n\nDescription\n-----------\nA Hydrator Action plugin to efficiently export data from Oracle to HDFS or local file system. The plugin uses\nOracle's command line tools to export data. The data exported from this tool can then be used in Hydrator pipelines.\n\n\nUse Case\n--------\nA Hydrator user would like to export oracle data onto HDFS or local file system using an action plugin\nthat exports Oracle data using the Oracle bulk export tool as opposed to using JDBC.\n\n\nProperties\n----------\n\n**oracleServerHostname:** Hostname of the remote Oracle Host.\n\n**oracleServerSSHPort:** Port to use to SSH to the remote Oracle Host. Defaults to 22.\n\n**oracleServerSSHUsername:** Username to use to connect to the remote Oracle Host via SSH.\n\n**oracleServerSSHAuthMechanism :** Mechanism to perform the secure shell action. Acceptable values are Private Key,\nPassword.\n\n**oracleServerSSHPassword:** Password to use to connect to the remote Oracle Host via SSH. This will be ignored\nwhen 'Private Key' is used as the authentication mechanism.\n\n**oracleServerSSHPrivateKey:** The private key to be used to perform the secure shell action. This will be ignored\nwhen 'Password' is used as the authentication mechanism.\n\n**passphrase:** Passphrase used to decrypt the provided private key in \"privateKey\". This will be ignored\nwhen 'Password' is used as the authentication mechanism.\n\n**dbUsername:** Username to connect to the Oracle database.\n\n**dbPassword:** Password to connect the Oracle database.\n\n**oracleHome:** Absolute path of the ``ORACLE_HOME`` environment variable on the Oracle server host.\nThis will be used to run the Oracle Spool utility.\n\n**oracleSID:** Oracle System ID(SID). This is used to uniquely identify a particular database on the system.\n\n**queryToExecute:** Query to be executed to export.For example: ``select * from test where name='cask'``;\n\n**tmpSQLScriptFile:** Full path of the local temporary SQL script file which needs to be created.\nIt will be removed once the SQL command is executed.  Default is /tmp/tmpHydrator.sql. If 'commandToRun' input is used,\nthen filename has to be as same as in 'commandToRun'.\n\n**commandToRun:** Oracle command to be executed on the Oracle host. When not provided, plugin will create\nthe command based on the input values provided in 'dbUsername', 'dbPassword', 'oracleHome', 'oracleSID',\n'queryToExecute' and 'tmpSQLScriptDirectory'.\nFormat should be oracleHome/bin/sqlplus -s dbUsername/dbPassword@oracleSID @tmpSQLScriptFile\n\n**outputPath:** Hdfs or local filesystem path where output file will be exported.\n\n**format:** Format of the output file. Acceptable values are CSV, TSV, PSV.\n\n\nExample\n-------\nThis example exports data from oracle server example.com using oracle user:\n\n    {\n        \"name\": \"OracleExportAction\",\n          \"plugin\": {\n            \"name\": \"OracleExportAction\",\n            \"type\": \"action\",\n            \"label\": \"OracleExportAction\",\n            \"artifact\": {\n              \"name\": \"core-plugins\",\n              \"version\": \"1.5.0-SNAPSHOT\",\n              \"scope\": \"SYSTEM\"\n          },\n          \"properties\": {\n              \"oracleServerHostname\": \"example.com\",\n              \"oracleServerSSHPort\": \"22\",\n              \"oracleServerSSHUsername\": \"oracle\",\n              \"oracleServerSSHAuthMechanism\": \"Password\",\n              \"oracleServerSSHPassword\": \"oracle@123\",\n              \"oracleServerSSHPrivateKey\": \"\",\n              \"oracleServerSSHPassphrase\": \"\",\n              \"dbUsername\": \"system\",\n              \"dbPassword\": \"cask\",\n              \"oracleHome\": \"/u01/app/oracle/product/11.2.0/xe\",\n              \"oracleSID\": \"cask\",\n              \"queryToExecute\": \"select * from test where name='cask';\",\n              \"tmpSQLScriptFile\": \"/tmp/tmpHydrator.sql\",\n              \"commandToRun\": \"\",\n              \"outputPath\" : \"/tmp/data.csv\",\n              \"format\" : \"CSV\"\n          }\n    }"
  }
}
