{
  "properties": {
    "doc.DatabaseArgumentSetter-action": "# Database Action\n\n\nDescription\n-----------\nAction that converts table column into pipeline arguments.\n\n\nUse Case\n--------\nThe action can be used whenever you want to pass data from database as arguments to a data pipeline.\nFor example, you may want to read a particular table at runtime to set arguments for the pipeline.\n\n\nProperties\n----------\n**Driver Name:** Name of the JDBC driver to use.\n\n**Connection String:** JDBC connection string including database name.\n\n**Database:** Database name.\n\n**Table:** Table name.\n\n**Argument selection conditions:** A set of conditions for identifying the arguments to run a pipeline. Multiple conditions can be specified in the format\n                                   column1=<column1-value>;column2=<column2-value>.\n\n**Username:** User identity for connecting to the specified database.\n\n**Password:** Password to use to connect to the specified database.\n\n**Connection Arguments:** A list of arbitrary string key/value pairs as connection arguments. These arguments\nwill be passed to the JDBC driver as connection arguments for JDBC drivers that may need additional configurations.\n\n**Arguments column:** Name of the column that contains the arguments.\n\nExample\n-------\nSuppose you have a configuration management database and you want to read a particular table at runtime to set arguments for the pipeline, including the source configuration, the transformations, the sink configuration, etc. \n\n```\nDriver Name: \"postgres\"\nConnection String: \"jdbc:postgresql://localhost:5432/configuration\"\nDatabase: \"configuration\"\nTable: \"files\"\nArgument selection conditions: \"file_id=1\"\nArguments column: \"file_name\"\n```\n",
    "widgets.DatabaseArgumentSetter-action": "{\n  \"metadata\": {\"spec-version\": \"1.5\"},\n  \"configuration-groups\": [\n    {\n      \"label\": \"Connection\",\n      \"properties\": [\n        {\n          \"widget-type\": \"textbox\",\n          \"name\": \"jdbcPluginName\",\n          \"label\": \"Plugin Name\"\n        },\n        {\n          \"widget-type\": \"textbox\",\n          \"name\": \"jdbcPluginType\",\n          \"label\": \"Plugin Type\",\n          \"widget-attributes\": {\"default\": \"jdbc\"}\n        },\n        {\n          \"widget-type\": \"textbox\",\n          \"name\": \"connectionString\",\n          \"label\": \"Connection String\"\n        }\n      ]\n    },\n    {\n      \"label\": \"Credentials\",\n      \"properties\": [\n        {\n          \"widget-type\": \"textbox\",\n          \"name\": \"user\",\n          \"label\": \"Username\"\n        },\n        {\n          \"widget-type\": \"password\",\n          \"name\": \"password\",\n          \"label\": \"Password\"\n        }\n      ]\n    },\n    {\n      \"label\": \"Configuration\",\n      \"properties\": [\n        {\n          \"widget-type\": \"textbox\",\n          \"name\": \"databaseName\",\n          \"label\": \"Database\"\n        },\n        {\n          \"widget-type\": \"textbox\",\n          \"name\": \"tableName\",\n          \"label\": \"Table\"\n        },\n        {\n          \"widget-type\": \"keyvalue\",\n          \"name\": \"argumentSelectionConditions\",\n          \"label\": \"Argument Selection Conditions\",\n          \"widget-attributes\": {\n            \"kv-delimiter\": \"=\",\n            \"key-placeholder\": \"Column name\",\n            \"value-placeholder\": \"Value\",\n            \"delimiter\": \";\",\n            \"showDelimiter\": \"false\"\n          }\n        },\n        {\n          \"widget-type\": \"csv\",\n          \"name\": \"argumentsColumns\",\n          \"label\": \"Argument columns\",\n          \"widget-attributes\": {\"value-placeholder\": \"Column name\"}\n        }\n      ]\n    },\n    {\n      \"label\": \"Advanced\",\n      \"properties\": [{\n        \"widget-type\": \"keyvalue\",\n        \"name\": \"connectionArguments\",\n        \"label\": \"Connection Arguments\",\n        \"widget-attributes\": {\n          \"kv-delimiter\": \"=\",\n          \"key-placeholder\": \"Key\",\n          \"value-placeholder\": \"Value\",\n          \"delimiter\": \";\",\n          \"showDelimiter\": \"false\"\n        }\n      }]\n    }\n  ],\n  \"display-name\": \"Database Argument Setter\",\n  \"icon\": {\n    \"arguments\": {\"data\": \"data:image/png;base64,iVBORw0KGgoAAAANSUhEUgAAADAAAAAwCAMAAABg3Am1AAAAgVBMVEUAAABVVXFgZGhgYmlfY2hf\\r\\nY2hfY2lfY2hfY2hfY2hhYWpfY2dfY2hfY2hfY2dfY2hfY2hiYmxfYmheY2hfY2hgYGpfY2hfY2hf\\r\\nY2hkZGRgY2hjY2NfYmheZWhfY2hgY2dfY2hfY2lgZGlAgIBfY2hfZGdeY2heYmphYWdgYGgAAADp\\r\\n9FLvAAAAK3RSTlMACUBwk7bZ3+v/HXnE+T66/hqzNuUY6p/iF10Syky8SN2GOATzj2dBKiABhpko\\r\\n/AAAALpJREFUeAHt1UcOwyAURdGX6vy4996797/ATHEDCSkznzkScL8AFwm3++P5eisfoo/yfj0f\\r\\n9xs4vqqm04auqV8cM0yLDlmmgT3bIQ7HxobrEZfnYsUPSCDwwQpJKAQrIqFIYoHEliQOLXetEuFi\\r\\n8WjEYCXi4UvAUlLReKcKWJTF4IozWi8gLwdH7hHtShclTpTFSemqblpstE1d8Up3RT+M07wAyzyN\\r\\nQ190V+mr9H9LSzz3wtLyX9ZF7AdyPSslOUpzqAAAAABJRU5ErkJg\"},\n    \"type\": \"inline\"\n  }\n}"
  },
  "parents": [
    "system:cdap-data-pipeline[6.1.1,7.0.0-SNAPSHOT)",
    "system:cdap-data-streams[6.1.1,7.0.0-SNAPSHOT)"
  ]
}